grai_source_dbt_cloud/__init__.py
grai_source_dbt_cloud/base.py
grai_source_dbt_cloud/loader.py
grai_source_dbt_cloud/py.typed
grai_source_dbt_cloud-0.1.5.dist-info/METADATA
grai_source_dbt_cloud-0.1.5.dist-info/WHEEL
grai_source_dbt_cloud-0.1.5.dist-info/RECORD
